tpds_extension/symmetric_auth/extension.yaml
tpds_extension/symmetric_auth/setup.py
tpds_extension/symmetric_auth/version.py
tpds_extension/symmetric_auth/TrustFlex/Symm Auth Shared Key.ipynb
tpds_extension/symmetric_auth/TrustFlex/firmware.zip
tpds_extension/symmetric_auth/TrustFlex/slot_5_secret_key.h
tpds_extension/symmetric_auth/TrustFlex/assets/Symmetric Authentication.md
tpds_extension/symmetric_auth/TrustFlex/assets/images/c-snippet.PNG
tpds_extension/symmetric_auth/TrustFlex/assets/images/crypto-assets.png
tpds_extension/symmetric_auth/TrustFlex/assets/images/symmetric key auth.png
tpds_extension/symmetric_auth/TrustFlex/assets/images/td-accessory-symmetric-auth.png
tpds_extension/symmetric_auth/TrustFlex/assets/images/usecase_steps.png
tpds_extension/symmetric_auth/TrustFlex/assets/python/symmetric_authentication.py
tpds_extension_spg_symmetric_auth-2.2.4.dist-info/METADATA
tpds_extension_spg_symmetric_auth-2.2.4.dist-info/WHEEL
tpds_extension_spg_symmetric_auth-2.2.4.dist-info/top_level.txt
tpds_extension_spg_symmetric_auth-2.2.4.dist-info/RECORD
